clld_morphology_plugin/__init__.py
clld_morphology_plugin/datatables.py
clld_morphology_plugin/interfaces.py
clld_morphology_plugin/models.py
clld_morphology_plugin/static/clld-morphology.css
clld_morphology_plugin/static/clld-morphology.js
clld_morphology_plugin/templates/derivationalprocess/detail_html.mako
clld_morphology_plugin/templates/derivationalprocess/index_html.mako
clld_morphology_plugin/templates/form/detail_html.mako
clld_morphology_plugin/templates/form/index_html.mako
clld_morphology_plugin/templates/gloss/detail_html.mako
clld_morphology_plugin/templates/inflectionalcategory/detail_html.mako
clld_morphology_plugin/templates/inflectionalcategory/index_html.mako
clld_morphology_plugin/templates/inflectionalvalue/detail_html.mako
clld_morphology_plugin/templates/inflectionalvalue/index_html.mako
clld_morphology_plugin/templates/lexeme/detail_html.mako
clld_morphology_plugin/templates/lexeme/index_html.mako
clld_morphology_plugin/templates/meaning/detail_html.mako
clld_morphology_plugin/templates/meaning/index_html.mako
clld_morphology_plugin/templates/morph/detail_html.mako
clld_morphology_plugin/templates/morph/index_html.mako
clld_morphology_plugin/templates/morpheme/detail_html.mako
clld_morphology_plugin/templates/morpheme/index_html.mako
clld_morphology_plugin/templates/morphology_util.mako
clld_morphology_plugin/templates/morphophonologicalchange/detail_html.mako
clld_morphology_plugin/templates/morphophonologicalchange/index_html.mako
clld_morphology_plugin/templates/pos/detail_html.mako
clld_morphology_plugin/templates/pos/index_html.mako
clld_morphology_plugin/templates/stem/detail_html.mako
clld_morphology_plugin/templates/stem/index_html.mako
clld_morphology_plugin/templates/wordform/detail_html.mako
clld_morphology_plugin/templates/wordform/index_html.mako
clld_morphology_plugin/util.py
clld_morphology_plugin-0.1.2.dist-info/LICENSE
clld_morphology_plugin-0.1.2.dist-info/METADATA
clld_morphology_plugin-0.1.2.dist-info/WHEEL
clld_morphology_plugin-0.1.2.dist-info/entry_points.txt
clld_morphology_plugin-0.1.2.dist-info/RECORD
